aiopybit/__init__.py
aiopybit/client.py
aiopybit/http_client.py
aiopybit/protocols.py
aiopybit/websocket_client.py
aiopybit/websocket_manager.py
aiopybit/http_methods/__init__.py
aiopybit/http_methods/account_methods.py
aiopybit/http_methods/market_methods.py
aiopybit/http_methods/order_methods.py
aiopybit/http_methods/position_methods.py
aiopybit/websocket_methods/__init__.py
aiopybit/websocket_methods/market_streams.py
aiopybit/websocket_methods/private_streams.py
aiopybit-0.1.2.dist-info/licenses/LICENSE
aiopybit-0.1.2.dist-info/METADATA
aiopybit-0.1.2.dist-info/WHEEL
aiopybit-0.1.2.dist-info/top_level.txt
aiopybit-0.1.2.dist-info/RECORD
