Metadata-Version: 2.4
Name: aiopybit
Version: 0.1.2
Summary: Asynchronous Python client for the ByBit API
Author-email: Tsunami43 <n3m0_22@mail.ru>
License-Expression: MIT
Project-URL: Repository, https://github.com/Tsunami43/aiopybit.git
Project-URL: Homepage, https://github.com/Tsunami43/aiopybit
Keywords: bybit,websocket,crypto,cryptocurrency,trading,exchange,async,aiohttp,python,api,websockets,market-data,orderbook,ticker,trades,bot
Requires-Python: <4.0,>=3.10
License-File: LICENSE
Requires-Dist: aiohttp>=3.12.15
Requires-Dist: websockets>=15.0.1
Dynamic: license-file
